orbs/__init__.py
orbs/_constant.py
orbs/api_client.py
orbs/api_server.py
orbs/browser_factory.py
orbs/cli.py
orbs/config.py
orbs/dependency.py
orbs/exception.py
orbs/guard.py
orbs/listener_manager.py
orbs/log.py
orbs/mobile_factory.py
orbs/report_generator.py
orbs/report_listener.py
orbs/runner.py
orbs/thread_context.py
orbs/utils.py
orbs/keyword/__init__.py
orbs/keyword/locator.py
orbs/keyword/mobile.py
orbs/keyword/web.py
orbs/spy/__init__.py
orbs/spy/base.py
orbs/spy/mobile.py
orbs/spy/web.py
orbs/spy/js/web_spy_listener.js
orbs/templates/jinja/features/feature.feature.j2
orbs/templates/jinja/listeners/listener.py.j2
orbs/templates/jinja/object_repository/WebElementEntity.xml.j2
orbs/templates/jinja/steps/step.py.j2
orbs/templates/jinja/testcases/testcase.py.j2
orbs/templates/jinja/testsuite_collections/testsuite_collection.yml.j2
orbs/templates/jinja/testsuites/testsuite.py.j2
orbs/templates/jinja/testsuites/testsuite.yml.j2
orbs/templates/project/.dockerignore
orbs/templates/project/.env.dev
orbs/templates/project/.env.prod
orbs/templates/project/.env.stagging
orbs/templates/project/.gitignore
orbs/templates/project/Dockerfile
orbs/templates/project/README.md
orbs/templates/project/__init__.py
orbs/templates/project/main.py
orbs/templates/project/pytest.ini
orbs/templates/project/requirements.txt
orbs/templates/project/.vscode/launch.json
orbs/templates/project/include/environment.py
orbs/templates/project/include/features/login.feature
orbs/templates/project/include/steps/login_steps.py
orbs/templates/project/listeners/.gitkeep
orbs/templates/project/settings/browser.properties
orbs/templates/project/settings/mobile.properties
orbs/templates/project/settings/platform.properties
orbs/templates/project/settings/server.properties
orbs/templates/project/testcases/login.py
orbs/templates/project/testsuite_collections/.gitkeep
orbs/templates/project/testsuites/login.py
orbs/templates/project/testsuites/login.yml
orbs_cli-0.1.6.dist-info/licenses/LICENSE
tests/test_report_generator.py
orbs_cli-0.1.6.dist-info/METADATA
orbs_cli-0.1.6.dist-info/WHEEL
orbs_cli-0.1.6.dist-info/entry_points.txt
orbs_cli-0.1.6.dist-info/top_level.txt
orbs_cli-0.1.6.dist-info/RECORD
