Metadata-Version: 2.4
Name: orbs-cli
Version: 0.1.6
Summary: Orbs - an automation framework for Web, Mobile (Appium), and API testing designed to grow with your team
Author-email: Muhamad Badru Salam <badrusalam760@gmail.com>
License: Apache-2.0
Project-URL: Homepage, https://github.com/badrusalam11/orbs-cli
Project-URL: Repository, https://github.com/badrusalam11/orbs-cli
Project-URL: Issues, https://github.com/badrusalam11/orbs-cli/issues
Requires-Python: >=3.8
License-File: LICENSE
Requires-Dist: typer[all]
Requires-Dist: flask
Requires-Dist: pyyaml
Requires-Dist: apscheduler
Requires-Dist: jinja2
Requires-Dist: requests
Requires-Dist: python-dotenv
Requires-Dist: Appium-Python-Client
Requires-Dist: selenium
Requires-Dist: behave
Requires-Dist: reportlab
Requires-Dist: InquirerPy
Dynamic: license-file
